Workbook

Sheet Read Me
A1: The Ledger
A2: A tool with one job: answer five questions on payday, in five minutes.
A3: SPREADSHEET FORMAT VERSION
A4: 1.0
A7: WHAT THIS IS
A8: The non-coder version of Aaron's private debt-elimination app, from the book Splinched. It is not a budgeting
A9: app. It does not track every dollar. It answers: what do I owe and how fast is it shrinking, can I cover the
A10: month, how much can I attack with, where does it go, and did the autopays clear.
A12: THE TABS
A13: • Accounts — your debts + checking. Edit the blue cells. Current Balance is derived from Snapshots.
A14: • Snapshots — your dated balance history. Add a row each payday; the latest one drives everything.
A15: • Glance — the top-line numbers: total owed, monthly interest burn, projected debt-free date.
... A40: Total owed: $65,360.89 · Monthly interest burn: $394.32 · Default monthly attack: $1,000

Sheet Accounts
A1: Accounts
A2: Edit the blue cells. Current Balance is derived from the latest Snapshot.
A4: Slug | B4: Name | C4: Type | D4: Status | E4: APR % | F4: Min Payment | G4: Attack Alloc | H4: Autopay | I4: Autopay Amt | J4: Cadence | K4: Is Debt? | L4: Latest Snapshot | M4: Current Balance
A5: nordstrom | B5: Nordstrom | C5: credit_card | D5: active | E5: 30.15 | F5: 0 | G5: 0 | H5: 1 | I5: 0 | J5: monthly | K5: =IF(AND(OR($D5="active",$D5="unknown"),$C5<>"checking",$C5<>"savings"),1,0) -> 1 | L5: =IF(COUNTIF(Snapshots!$A$5:$A$200,$A5)=0,"",SUMPRODUCT(MAX((Snapshots!$A$5:$A$200=$A5)*Snapshots!$C$5:$C$200))) -> 46168 | M5: =IF(COUNTIF(Snapshots!$A$5:$A$200,$A5)=0,0,SUMPRODUCT((Snapshots!$A$5:$A$200=$A5)*(Snapshots!$C$5:$C$200=$L5)*Snapshots!$D$5:$D$200)) -> 161.89
A6: pnc | B6: PNC | C6: credit_card | D6: active | E6: 29.24 | F6: 192 | G6: 1000 | H6: 1 | I6: 192 | J6: monthly | K6: =IF(AND(OR($D6="active",$D6="unknown"),$C6<>"checking",$C6<>"savings"),1,0) -> 1 | L6: =IF(COUNTIF(Snapshots!$A$5:$A$200,$A6)=0,"",SUMPRODUCT(MAX((Snapshots!$A$5:$A$200=$A6)*Snapshots!$C$5:$C$200))) -> 46168 | M6: =IF(COUNTIF(Snapshots!$A$5:$A$200,$A6)=0,0,SUMPRODUCT((Snapshots!$A$5:$A$200=$A6)*(Snapshots!$C$5:$C$200=$L6)*Snapshots!$D$5:$D$200)) -> 5801.79
A7: capital-one | B7: Capital One | C7: credit_card | D7: active | E7: 28.49 | F7: 84 | G7: 0 | H7: 1 | I7: 84 | J7: monthly | K7: =IF(AND(OR($D7="active",$D7="unknown"),$C7<>"checking",$C7<>"savings"),1,0) -> 1 | L7: =IF(COUNTIF(Snapshots!$A$5:$A$200,$A7)=0,"",SUMPRODUCT(MAX((Snapshots!$A$5:$A$200=$A7)*Snapshots!$C$5:$C$200))) -> 46168 | M7: =IF(COUNTIF(Snapshots!$A$5:$A$200,$A7)=0,0,SUMPRODUCT((Snapshots!$A$5:$A$200=$A7)*(Snapshots!$C$5:$C$200=$L7)*Snapshots!$D$5:$D$200)) -> 2461.27
A8: ikea | B8: IKEA | C8: credit_card | D8: active | E8: 21.99 | F8: 36 | G8: 0 | H8: 1 | I8: 36 | J8: monthly | K8: =IF(AND(OR($D8="active",$D8="unknown"),$C8<>"checking",$C8<>"savings"),1,0) -> 1 | L8: =IF(COUNTIF(Snapshots!$A$5:$A$200,$A8)=0,"",SUMPRODUCT(MAX((Snapshots!$A$5:$A$200=$A8)*Snapshots!$C$5:$C$200))) -> 46168 | M8: =IF(COUNTIF(Snapshots!$A$5:$A$200,$A8)=0,0,SUMPRODUCT((Snapshots!$A$5:$A$200=$A8)*(Snapshots!$C$5:$C$200=$L8)*Snapshots!$D$5:$D$200)) -> 1012.24
A9: sofi | B9: SoFi | C9: loan | D9: active | E9: 14.41 | F9: 310.97 | G9: 0 | H9: 1 | I9: 310.97 | J9: monthly | K9: =IF(AND(OR($D9="active",$D9="unknown"),$C9<>"checking",$C9<>"savings"),1,0) -> 1 | L9: =IF(COUNTIF(Snapshots!$A$5:$A$200,$A9)=0,"",SUMPRODUCT(MAX((Snapshots!$A$5:$A$200=$A9)*Snapshots!$C$5:$C$200))) -> 46168 | M9: =IF(COUNTIF(Snapshots!$A$5:$A$200,$A9)=0,0,SUMPRODUCT((Snapshots!$A$5:$A$200=$A9)*(Snapshots!$C$5:$C$200=$L9)*Snapshots!$D$5:$D$200)) -> 5979.44
A10: fedloan-student | B10: FedLoan Student | C10: student_loan | D10: unknown | E10: 5 | F10: 0 | G10: 0 | H10: 0 | I10: 0 | K10: =IF(AND(OR($D10="active",$D10="unknown"),$C10<>"checking",$C10<>"savings"),1,0) -> 1 | L10: =IF(COUNTIF(Snapshots!$A$5:$A$200,$A10)=0,"",SUMPRODUCT(MAX((Snapshots!$A$5:$A$200=$A10)*Snapshots!$C$5:$C$200))) -> 46168 | M10: =IF(COUNTIF(Snapshots!$A$5:$A$200,$A10)=0,0,SUMPRODUCT((Snapshots!$A$5:$A$200=$A10)*(Snapshots!$C$5:$C$200=$L10)*Snapshots!$D$5:$D$200)) -> 24022
A11: apple | B11: Apple | C11: bnpl | D11: active | E11: 0 | F11: 375.55 | G11: 0 | H11: 1 | I11: 375.55 | J11: monthly_eom | K11: =IF(AND(OR($D11="active",$D11="unknown"),$C11<>"checking",$C11<>"savings"),1,0) -> 1 | L11: =IF(COUNTIF(Snapshots!$A$5:$A$200,$A11)=0,"",SUMPRODUCT(MAX((Snapshots!$A$5:$A$200=$A11)*Snapshots!$C$5:$C$200))) -> 46168 | M11: =IF(COUNTIF(Snapshots!$A$5:$A$200,$A11)=0,0,SUMPRODUCT((Snapshots!$A$5:$A$200=$A11)*(Snapshots!$C$5:$C$200=$L11)*Snapshots!$D$5:$D$200)) -> 18112.91
A12: jenius | B12: Jenius | C12: credit_card | D12: active | E12: 0 | F12: 200 | G12: 0 | H12: 1 | I12: 200 | J12: biweekly | K12: =IF(AND(OR($D12="active",$D12="unknown"),$C12<>"checking",$C12<>"savings"),1,0) -> 1 | L12: =IF(COUNTIF(Snapshots!$A$5:$A$200,$A12)=0,"",SUMPRODUCT(MAX((Snapshots!$A$5:$A$200=$A12)*Snapshots!$C$5:$C$200))) -> 46168 | M12: =IF(COUNTIF(Snapshots!$A$5:$A$200,$A12)=0,0,SUMPRODUCT((Snapshots!$A$5:$A$200=$A12)*(Snapshots!$C$5:$C$200=$L12)*Snapshots!$D$5:$D$200)) -> 5075.84
A13: paypal | B13: PayPal | C13: bnpl | D13: active | E13: 0 | F13: 75 | G13: 0 | H13: 1 | I13: 75 | J13: monthly | K13: =IF(AND(OR($D13="active",$D13="unknown"),$C13<>"checking",$C13<>"savings"),1,0) -> 1 | L13: =IF(COUNTIF(Snapshots!$A$5:$A$200,$A13)=0,"",SUMPRODUCT(MAX((Snapshots!$A$5:$A$200=$A13)*Snapshots!$C$5:$C$200))) -> 46168 | M13: =IF(COUNTIF(Snapshots!$A$5:$A$200,$A13)=0,0,SUMPRODUCT((Snapshots!$A$5:$A$200=$A13)*(Snapshots!$C$5:$C$200=$L13)*Snapshots!$D$5:$D$200)) -> 2733.51
A14: amex | B14: Amex | C14: credit_card | D14: paid_off | E14: 29.99 | F14: 0 | G14: 0 | H14: 0 | I14: 0 | K14: =IF(AND(OR($D14="active",$D14="unknown"),$C14<>"checking",$C14<>"savings"),1,0) -> 0 | L14: =IF(COUNTIF(Snapshots!$A$5:$A$200,$A14)=0,"",SUMPRODUCT(MAX((Snapshots!$A$5:$A$200=$A14)*Snapshots!$C$5:$C$200))) -> 46168 | M14: =IF(COUNTIF(Snapshots!$A$5:$A$200,$A14)=0,0,SUMPRODUCT((Snapshots!$A$5:$A$200=$A14)*(Snapshots!$C$5:$C$200=$L14)*Snapshots!$D$5:$D$200)) -> 0
A15: checking | B15: Checking | C15: checking | D15: active | E15: 0 | F15: 0 | G15: 0 | H15: 0 | I15: 0 | K15: =IF(AND(OR($D15="active",$D15="unknown"),$C15<>"checking",$C15<>"savings"),1,0) -> 0 | L15: =IF(COUNTIF(Snapshots!$A$5:$A$200,$A15)=0,"",SUMPRODUCT(MAX((Snapshots!$A$5:$A$200=$A15)*Snapshots!$C$5:$C$200))) | M15: =IF(COUNTIF(Snapshots!$A$5:$A$200,$A15)=0,0,SUMPRODUCT((Snapshots!$A$5:$A$200=$A15)*(Snapshots!$C$5:$C$200=$L15)*Snapshots!$D$5:$D$200)) -> 0

Sheet Snapshots
A1: Snapshots
A2: Dated balance readings. Add a row each payday — the latest per account is the current balance.
A4: Slug | B4: Account | C4: Date | D4: Balance | E4: Notes
A5: nordstrom | B5: Nordstrom | C5: 46168 | D5: 161.89 | E5: Seed snapshot (2026-05-26)
A6: pnc | B6: PNC | C6: 46168 | D6: 5801.79 | E6: Seed snapshot (2026-05-26)
A7: capital-one | B7: Capital One | C7: 46168 | D7: 2461.27 | E7: Seed snapshot (2026-05-26)
A8: ikea | B8: IKEA | C8: 46168 | D8: 1012.24 | E8: Seed snapshot (2026-05-26)
A9: sofi | B9: SoFi | C9: 46168 | D9: 5979.44 | E9: Seed snapshot (2026-05-26)
A10: fedloan-student | B10: FedLoan Student | C10: 46168 | D10: 24022 | E10: Seed snapshot (2026-05-26)
A11: apple | B11: Apple | C11: 46168 | D11: 18112.91 | E11: Seed snapshot (2026-05-26)
A12: jenius | B12: Jenius | C12: 46168 | D12: 5075.84 | E12: Seed snapshot (2026-05-26)
A13: paypal | B13: PayPal | C13: 46168 | D13: 2733.51 | E13: Seed snapshot (2026-05-26)
A14: amex | B14: Amex | C14: 46168 | D14: 0 | E14: Seed snapshot (2026-05-26)
A16: (Checking intentionally not seeded — snapshot it on your first payday.)

Sheet Glance
A1: Glance
A2: Where am I, and what do I do next?
A4: Total owed | B4: =SUMPRODUCT(Accounts!$K$5:$K$15,Accounts!$M$5:$M$15) -> 65360.89
A5: Monthly interest burn | B5: =SUMPRODUCT(Accounts!$K$5:$K$15,Accounts!$M$5:$M$15,Accounts!$E$5:$E$15)/1200 -> 394.31649
A6: Default monthly attack | B6: =1000 -> 1000
A7: Cash runway status | B7: =Runway!$B$8 -> unknown
A8: 30-day change | B8: —
A9: Projected debt-free date | B9: → run the Projection & Sandbox tool
A10: Total interest to payoff | B10: → run the Projection & Sandbox tool
A12: 30-day change needs a month of history — your first month is the baseline, not zero.
A13: Your debt-free date and what-if sandbox come from the companion tool, run against this file.

Sheet Runway
A1: Cash Runway
A2: Can you cover what's due before your next payday? Enter checking + the obligations in the window.
A4: Checking balance (enter)
A5: Next payday (enter)
A6: Total obligations before payday | B6: =SUMPRODUCT($C$11:$C$25,$D$11:$D$25) -> 0
A7: Free to attack | B7: =IF($B$4="","",$B$4-$B$6)
A8: Runway status | B8: =IF($B$4="","unknown",IF($B$7<0,"underwater",IF($B$7<200,"tight","healthy"))) -> unknown
A10: Description | B10: Type | C10: Amount | D10: Include 1/0
A11: PNC autopay | B11: autopay | C11: 192 | D11: 0
A12: Capital One autopay | B12: autopay | C12: 84 | D12: 0
A13: IKEA autopay | B13: autopay | C13: 36 | D13: 0
A14: SoFi autopay | B14: autopay | C14: 310.97 | D14: 0
A15: Apple autopay | B15: autopay | C15: 375.55 | D15: 0
A16: Jenius autopay | B16: autopay | C16: 200 | D16: 0
A17: PayPal autopay | B17: autopay | C17: 75 | D17: 0
A27: Set Include=1 for each obligation that actually falls before your next payday. Healthy ≥ $200 free; tight < $200; underwater < $0.

Sheet Recurring
A1: Recurring Expenses
A2: Your fixed monthly bills. Keep this current; it feeds the runway.
A4: Name | B4: Amount | C4: Day of Month | D4: Category | E4: Active 1/0
A17: (Day of month: 0 = last day. Example: Rent · 1500 · 1 · Bills · 1)

Sheet Projection & Sandbox
A1: Projection & Sandbox
A2: Your real debt-free date and the what-if sandbox — computed by the companion tool.
A5: WHY THIS ISN'T A TAB OF FORMULAS
A6: Projecting a payoff means simulating every month: apply interest, pay minimums, attack the highest-APR debt, and
A7: when a debt dies, cascade its freed-up payment to the next target. That running, order-dependent state is something
A8: a spreadsheet can't do faithfully — but it's exactly what the companion Projection & Sandbox tool does.
A10: HOW TO USE IT
A11: 1. Keep Accounts and Snapshots clean and current (the tool reads your debts and balances from them).
A12: 2. Open the Projection & Sandbox tool and point it at this spreadsheet.
A13: 3. It computes your real month-by-month payoff and your debt-free date — from your numbers, not anyone else's.
A14: 4. Then play: bump your monthly attack, add a windfall, ramp side income — and watch your debt-free date move.
A16: WHAT IT READS FROM THIS FILE
... A22: The tool runs locally on your own machine — your numbers never leave your computer.

Sheet Milestones
A1: Milestones
A2: One current at a time. Earlier ones complete; later ones visible but patient.
A4: # | B4: Milestone | C4: Done when (condition) | D4: Status
A5: 1 | B5: Starter buffer | C5: $1,000 sitting in checking | D5: current
A6: 2 | B6: Resolve FedLoan | C6: Student-loan status & minimum known | D6: locked
A7: 3 | B7: Debt-free | C7: Total debt at $0 | D7: locked
A8: 4 | B8: Full emergency fund | C8: 3 months of expenses in liquid savings | D8: locked
A9: 5 | B9: Lindsay's exit ramp | C9: Manual — you decide when it's met | D9: locked
A10: 6 | B10: Retirement | C10: Manual — long horizon | D10: locked
